Metadata-Version: 1.1
Name: sphinxprettysearchresults
Version: 0.3.4
Summary: Decently styled search results for sphinx-doc projects
Home-page: https://github.com/TimKam/sphinx-pretty-searchresults
Author: Timotheus Kampik
Author-email: timotheus.kampik@gmail.com
License: MIT
Platform: any
Classifier: Development Status :: 4 - Beta
Classifier: Operating System :: OS Independent
Classifier: Programming Language :: Python
Classifier: Environment :: Plugins
Classifier: Intended Audience :: Developers
Classifier: License :: OSI Approved :: MIT License
Classifier: Topic :: Documentation
